djbver/__init__.py
djbver-0.0.2.dist-info/LICENSE
djbver-0.0.2.dist-info/METADATA
djbver-0.0.2.dist-info/WHEEL
djbver-0.0.2.dist-info/top_level.txt
djbver-0.0.2.dist-info/RECORD
