Metadata-Version: 2.1
Name: djbver
Version: 0.0.2
Summary: djbver
Home-page: https://github.com/springkjw/djbver
Author: Kwon Jaewon
Author-email: springkjw@gmail.com
License: MIT
Download-URL: https://github.com/springkjw/djbver/archive/0.0.2.tar.gz
Keywords: django,djbver,rest framework
Platform: UNKNOWN
Classifier: Natural Language :: Korean
Classifier: License :: OSI Approved :: MIT License
Classifier: Programming Language :: Python :: 3.6
Classifier: Programming Language :: Python :: 3.7
Classifier: Programming Language :: Python :: 3.8
Requires-Python: >=3.6
Requires-Dist: Django
Requires-Dist: djangorestframework
